simplepva/__init__.py
simplepva/simplepva.py
simplepva-0.1.0.dist-info/METADATA
simplepva-0.1.0.dist-info/WHEEL
simplepva-0.1.0.dist-info/top_level.txt
simplepva-0.1.0.dist-info/RECORD
