Metadata-Version: 2.1
Name: simplepva
Version: 0.1.0
Summary: Help your python code have parameters and arguments
Author: ph_thienphu1006
Author-email: phualan1006@gmail.com
Classifier: Programming Language :: Python :: 3
Classifier: License :: OSI Approved :: MIT License
Classifier: Operating System :: Microsoft :: Windows
